sentry_dingding/__init__.py
sentry_dingding/forms.py
sentry_dingding/plugin.py
cbs_sentry_dingding-1.0.24.dist-info/LICENSE
cbs_sentry_dingding-1.0.24.dist-info/METADATA
cbs_sentry_dingding-1.0.24.dist-info/WHEEL
cbs_sentry_dingding-1.0.24.dist-info/entry_points.txt
cbs_sentry_dingding-1.0.24.dist-info/top_level.txt
cbs_sentry_dingding-1.0.24.dist-info/RECORD
