Metadata-Version: 2.1
Name: cbs-sentry-dingding
Version: 1.0.24
Summary: A Sentry extension which send errors stats to DingDing Fix#22
Home-page: https://github.com/anshengme/sentry-dingding
Author: ansheng
Author-email: ianshengme@gmail.com
License: MIT
Keywords: sentry dingding
Platform: UNKNOWN
Classifier: Programming Language :: Python :: 2.7
Classifier: License :: OSI Approved :: MIT License
Requires-Dist: requests
Requires-Dist: sentry (>=9.0.0)
